linkwalker/spider/_types.py
linkwalker/spider/dynamic.py
linkwalker/spider/static.py
linkwalker-0.9.0.dist-info/licenses/LICENSE
linkwalker-0.9.0.dist-info/METADATA
linkwalker-0.9.0.dist-info/WHEEL
linkwalker-0.9.0.dist-info/top_level.txt
linkwalker-0.9.0.dist-info/RECORD
