Metadata-Version: 2.4
Name: linkwalker
Version: 0.9.0
Summary: Deep URL crawler for Python supporting dynamic and static content, domain restrictions, and callbacks.
Author-email: Ulus Vatansever <ulusvatansever@gmail.com>
License: MIT
Project-URL: Homepage, https://github.com/cvcvka5/linkwalker
Project-URL: Repository, https://github.com/cvcvka5/linkwalker
Project-URL: Documentation, https://github.com/cvcvka5/linkwalker#readme
Keywords: crawler,web-scraping,url,deep-crawl,automation
Classifier: Programming Language :: Python :: 3
Classifier: License :: OSI Approved :: MIT License
Classifier: Operating System :: OS Independent
Classifier: Development Status :: 4 - Beta
Classifier: Intended Audience :: Developers
Classifier: Topic :: Internet :: WWW/HTTP
Requires-Python: >=3.10
License-File: LICENSE
Dynamic: license-file
